fstring_builder/__init__.py
fstring_builder/enums.py
fstring_builder/fstring.py
fstring_builder/py.typed
fstring_builder/replacement_field.py
fstring_builder-0.2.0.dist-info/LICENSE
fstring_builder-0.2.0.dist-info/WHEEL
fstring_builder-0.2.0.dist-info/METADATA
fstring_builder-0.2.0.dist-info/RECORD
