Metadata-Version: 2.1
Name: fstring-builder
Version: 0.2.0
Summary: A human friendly format string builder
Author: Tim van Boxtel
Author-email: tim@vanboxtel.ca
Requires-Python: >=3.9,<4.0
Classifier: Programming Language :: Python :: 3
Classifier: Programming Language :: Python :: 3.9
Classifier: Programming Language :: Python :: 3.10
Classifier: Programming Language :: Python :: 3.11
